qaviton_helpers/__init__.py
qaviton_helpers/conditions.py
qaviton_helpers/converters.py
qaviton_helpers/diff.py
qaviton_helpers/importers.py
qaviton_helpers/inner_info.py
qaviton_helpers/object_helpers.py
qaviton_helpers/relative_path.py
qaviton_helpers/silly_helpers.py
qaviton_helpers/timers.py
qaviton_helpers/timeunit.py
qaviton_helpers-2019.11.1.13.59.3.22114.dist-info/LICENSE
qaviton_helpers-2019.11.1.13.59.3.22114.dist-info/METADATA
qaviton_helpers-2019.11.1.13.59.3.22114.dist-info/WHEEL
qaviton_helpers-2019.11.1.13.59.3.22114.dist-info/top_level.txt
qaviton_helpers-2019.11.1.13.59.3.22114.dist-info/RECORD
