Metadata-Version: 2.1
Name: qaviton-helpers
Version: 2019.11.1.13.59.3.22114
Summary: qaviton help functions to make things simple
Home-page: https://github.com/qaviton/qaviton_helpers
Author: qaviton
Author-email: info@qaviton.com
License: apache-2.0
Platform: UNKNOWN
Classifier: Programming Language :: Python :: 3.6
